sampen/__init__.py
sampen/normalize_data.py
sampen/sampen2.py
sampen-0.0.20.dist-info/LICENSE.txt
sampen-0.0.20.dist-info/METADATA
sampen-0.0.20.dist-info/WHEEL
sampen-0.0.20.dist-info/top_level.txt
sampen-0.0.20.dist-info/RECORD
